EasyConvert/__init__.py
EasyConvert/easyconvert.py
EasyTrain/__init__.py
EasyTrain/extensions.py
EasyTrain/run.py
EasyTrain/apis/__init__.py
EasyTrain/apis/baseml/__init__.py
EasyTrain/apis/baseml/baseml.py
EasyTrain/apis/baseml/config.py
EasyTrain/apis/basenn/__init__.py
EasyTrain/apis/basenn/basenn.py
EasyTrain/apis/basenn/config.py
EasyTrain/apis/mmedu/__init__.py
EasyTrain/apis/mmedu/config.py
EasyTrain/apis/mmedu/mmedu.py
EasyTrain/static/assets/clipboard-plus.svg
EasyTrain/static/assets/question-diamond.svg
EasyTrain/static/assets/x-square.svg
EasyTrain/static/css/baseml.css
EasyTrain/static/css/basenn.css
EasyTrain/static/css/bootstrap.min.css
EasyTrain/static/css/github.min.css
EasyTrain/static/css/style.css
EasyTrain/static/js/baseml.js
EasyTrain/static/js/basenn.js
EasyTrain/static/js/bootstrap.bundle.min.js
EasyTrain/static/js/clipboard.min.js
EasyTrain/static/js/echarts.min.js
EasyTrain/static/js/jquery-3.7.1.slim.min.js
EasyTrain/static/js/leader-line.min.js
EasyTrain/static/js/mmedu.js
EasyTrain/static/js/socket.io.js
EasyTrain/static/js/highlight/DIGESTS.md
EasyTrain/static/js/highlight/LICENSE
EasyTrain/static/js/highlight/README.md
EasyTrain/static/js/highlight/highlight.js
EasyTrain/static/js/highlight/highlight.min.js
EasyTrain/static/js/highlight/package.json
EasyTrain/static/js/highlight/es/__init__.py
EasyTrain/static/js/highlight/es/core.js
EasyTrain/static/js/highlight/es/core.min.js
EasyTrain/static/js/highlight/es/highlight.js
EasyTrain/static/js/highlight/es/highlight.min.js
EasyTrain/static/js/highlight/es/package.json
EasyTrain/static/js/highlight/languages/__init__.py
EasyTrain/static/js/highlight/languages/python.min.js
EasyTrain/static/js/highlight/styles/__init__.py
EasyTrain/static/js/highlight/styles/a11y-dark.min.css
EasyTrain/static/js/highlight/styles/a11y-light.min.css
EasyTrain/static/js/highlight/styles/agate.min.css
EasyTrain/static/js/highlight/styles/an-old-hope.min.css
easy_xedu-0.2.3.dist-info/METADATA
easy_xedu-0.2.3.dist-info/WHEEL
easy_xedu-0.2.3.dist-info/entry_points.txt
easy_xedu-0.2.3.dist-info/top_level.txt
easy_xedu-0.2.3.dist-info/RECORD
