Metadata-Version: 2.1
Name: easy-xedu
Version: 0.2.3
Summary: easy-xedu is a web-based platform for training deep learning models using MMEdu framework.
License: MIT
Requires-Python: >=3.6
Requires-Dist: flask
Requires-Dist: flask-cors
Requires-Dist: flask-socketio
Requires-Dist: pysimplegui
